{"trial_id": "03", "hyperparameters": {"space": [{"class_name": "Boolean", "config": {"name": "aug_geometric", "default": false, "conditions": []}}, {"class_name": "Boolean", "config": {"name": "aug_photometric", "default": false, "conditions": []}}, {"class_name": "Boolean", "config": {"name": "aug_noise", "default": false, "conditions": []}}, {"class_name": "Boolean", "config": {"name": "use_dropout", "default": false, "conditions": []}}, {"class_name": "Float", "config": {"name": "aug_contrast", "default": 0.1, "conditions": [], "min_value": 0.1, "max_value": 0.3, "step": null, "sampling": "linear"}}, {"class_name": "Float", "config": {"name": "aug_brightness", "default": 0.1, "conditions": [], "min_value": 0.1, "max_value": 0.3, "step": null, "sampling": "linear"}}, {"class_name": "Float", "config": {"name": "aug_noise_std", "default": 0.01, "conditions": [], "min_value": 0.01, "max_value": 0.1, "step": null, "sampling": "linear"}}], "values": {"aug_geometric": false, "aug_photometric": false, "aug_noise": false, "use_dropout": false, "aug_contrast": 0.2683387778040484, "aug_brightness": 0.1435108691225918, "aug_noise_std": 0.0633286198111054}}, "metrics": {"metrics": {"accuracy": {"direction": "max", "observations": [{"value": [0.5244755148887634], "step": 0}]}, "loss": {"direction": "min", "observations": [{"value": [0.873107373714447], "step": 0}]}, "val_accuracy": {"direction": "max", "observations": [{"value": [0.5], "step": 0}]}, "val_loss": {"direction": "min", "observations": [{"value": [0.6964356303215027], "step": 0}]}}}, "score": 0.5, "best_step": 0, "status": "COMPLETED", "message": null}